ml4paleo/__init__.py
ml4paleo/meshing/__init__.py
ml4paleo/segmentation/__init__.py
ml4paleo/segmentation/rf.py
ml4paleo/segmentation/segmenter.py
ml4paleo/volume_providers/__init__.py
ml4paleo/volume_providers/dicomvp.py
ml4paleo/volume_providers/imagevp.py
ml4paleo/volume_providers/io.py
ml4paleo/volume_providers/numpyvp.py
ml4paleo/volume_providers/volprov.ipynb
ml4paleo/volume_providers/volume_provider.py
ml4paleo/volume_providers/zarrvp.py
ml4paleo-0.1.0.dist-info/METADATA
ml4paleo-0.1.0.dist-info/WHEEL
ml4paleo-0.1.0.dist-info/RECORD
