Metadata-Version: 2.1
Name: ml4paleo
Version: 0.1.0
Summary: Deep learning computer vision pipelines for paleontological 3D reconstruction
License: Apache 2.0
Author: Jordan Matelsky
Author-email: j6k4m8@gmail.com
Requires-Python: >=3.9,<4.0
Classifier: License :: Other/Proprietary License
Classifier: Programming Language :: Python :: 3
Classifier: Programming Language :: Python :: 3.9
Classifier: Programming Language :: Python :: 3.10
Classifier: Programming Language :: Python :: 3.11
Provides-Extra: bossdb
Provides-Extra: dicom
Requires-Dist: Flask (>=2.2.2,<3.0.0)
Requires-Dist: Flask-Cors (>=3.0.10,<4.0.0)
Requires-Dist: Pillow (>=9.4.0,<10.0.0)
Requires-Dist: intern (>=1.4.0,<2.0.0) ; extra == "bossdb"
Requires-Dist: jque (>=0.1.3,<0.2.0)
Requires-Dist: marshmallow (>=3.19.0,<4.0.0)
Requires-Dist: matplotlib (>=3.6.3,<4.0.0)
Requires-Dist: numpy (>=1.24.1,<2.0.0)
Requires-Dist: numpy-stl (>=3.0.0,<4.0.0)
Requires-Dist: psutil (>=5.9.4,<6.0.0)
Requires-Dist: scikit-image (>=0.19.3,<0.20.0)
Requires-Dist: scikit-learn (>=1.2.1,<2.0.0)
Requires-Dist: tqdm (>=4.64.1,<5.0.0)
Requires-Dist: zarr (>=2.13.6,<3.0.0)
Requires-Dist: zmesh (>=1.6.2,<2.0.0)
